odoo/addons/ssi_l10n_id_taxform_faktur_pajak_klipajak/README.rst
odoo/addons/ssi_l10n_id_taxform_faktur_pajak_klipajak/__init__.py
odoo/addons/ssi_l10n_id_taxform_faktur_pajak_klipajak/__manifest__.py
odoo/addons/ssi_l10n_id_taxform_faktur_pajak_klipajak/menu.xml
odoo/addons/ssi_l10n_id_taxform_faktur_pajak_klipajak/data/policy_template_data.xml
odoo/addons/ssi_l10n_id_taxform_faktur_pajak_klipajak/i18n/ssi_l10n_id_taxform_faktur_pajak_klipajak.pot
odoo/addons/ssi_l10n_id_taxform_faktur_pajak_klipajak/models/__init__.py
odoo/addons/ssi_l10n_id_taxform_faktur_pajak_klipajak/models/buyer_document.py
odoo/addons/ssi_l10n_id_taxform_faktur_pajak_klipajak/models/faktur_pajak_keluaran.py
odoo/addons/ssi_l10n_id_taxform_faktur_pajak_klipajak/models/klikpajak_backend.py
odoo/addons/ssi_l10n_id_taxform_faktur_pajak_klipajak/models/klikpajak_parameter.py
odoo/addons/ssi_l10n_id_taxform_faktur_pajak_klipajak/models/res_company.py
odoo/addons/ssi_l10n_id_taxform_faktur_pajak_klipajak/security/ir.model.access.csv
odoo/addons/ssi_l10n_id_taxform_faktur_pajak_klipajak/static/description/icon.png
odoo/addons/ssi_l10n_id_taxform_faktur_pajak_klipajak/views/buyer_document_views.xml
odoo/addons/ssi_l10n_id_taxform_faktur_pajak_klipajak/views/faktur_pajak_keluaran_views.xml
odoo/addons/ssi_l10n_id_taxform_faktur_pajak_klipajak/views/klikpajak_backend_views.xml
odoo/addons/ssi_l10n_id_taxform_faktur_pajak_klipajak/views/res_company_views.xml
odoo14_addon_ssi_l10n_id_taxform_faktur_pajak_klipajak-14.0.1.3.0.dist-info/METADATA
odoo14_addon_ssi_l10n_id_taxform_faktur_pajak_klipajak-14.0.1.3.0.dist-info/WHEEL
odoo14_addon_ssi_l10n_id_taxform_faktur_pajak_klipajak-14.0.1.3.0.dist-info/top_level.txt
odoo14_addon_ssi_l10n_id_taxform_faktur_pajak_klipajak-14.0.1.3.0.dist-info/RECORD
